[
  {
    "model": "stablelm-3b-4e1t",
    "dataset": "agnews",
    "layer": 8,
    "K": 4,
    "q": 0.49333333333333335,
    "kappa_nearest": 0.05382488423720873,
    "kappa_min": 0.032994486061706976,
    "logit_q": -0.02666824708216118,
    "logKm1": 1.0986122886681098
  },
  {
    "model": "stablelm-3b-4e1t",
    "dataset": "agnews",
    "layer": 16,
    "K": 4,
    "q": 0.6066666666666666,
    "kappa_nearest": 0.08762858143439006,
    "kappa_min": 0.08064728603171571,
    "logit_q": 0.4333220626111302,
    "logKm1": 1.0986122886681098
  },
  {
    "model": "stablelm-3b-4e1t",
    "dataset": "agnews",
    "layer": 24,
    "K": 4,
    "q": 0.7066666666666667,
    "kappa_nearest": 0.2441530271259702,
    "kappa_min": 0.23927137429905676,
    "logit_q": 0.879249460193806,
    "logKm1": 1.0986122886681098
  },
  {
    "model": "stablelm-3b-4e1t",
    "dataset": "agnews",
    "layer": 32,
    "K": 4,
    "q": 0.7733333333333333,
    "kappa_nearest": 0.5268175688564547,
    "kappa_min": 0.43712726505995064,
    "logit_q": 1.2272296664902032,
    "logKm1": 1.0986122886681098
  }
]